py_cryptomus/__init__.py
py_cryptomus/main.py
py_cryptomus-0.1.1.dist-info/METADATA
py_cryptomus-0.1.1.dist-info/WHEEL
py_cryptomus-0.1.1.dist-info/top_level.txt
py_cryptomus-0.1.1.dist-info/RECORD
