Metadata-Version: 2.1
Name: py_cryptomus
Version: 0.1.1
Summary: Python wrapper for Cryptomus API based on the requests library.
Author: Ted Hackwell
Requires-Dist: requests>=2.25.1
